{
  "topic": "Warum können wir uns nicht an unsere Babyzeit erinnern?",
  "title": "Warum deine frühesten Erinnerungen verschwinden",
  "description": "Kurz erklärt: Warum wir uns nicht an die Babyzeit erinnern. Schlüsselbegriffe: Infantile Amnesie, Hippocampus, Gedächtnisentwicklung, Kindheitserinnerungen.",
  "hashtags": "#Psychologie #Gedächtnis #Kindheit #InfantileAmnesie",
  "script": "Nur wenige erinnern sich an ihr erstes Lebensjahr — warum?\nWeil unser Gehirn damals noch anders tickt.\nDer Hippocampus, unser Speicherzentrum, ist noch nicht voll entwickelt.\nSprache fehlt. Ohne Worte gibt es keine autobiografischen Erinnerungen.\nAußerdem räumt frühe Neurogenese alte Spuren weg.\nEltern erzählen später Geschichten. So formen wir Erinnerungen neu.\nJede Szene prägt uns, aber nicht als festes Bild.\nAha-Moment: Viele \"frühe Erinnerungen\" sind eigentlich Erzählungen.\nWelche deiner ersten Bilder ist wirklich deins?",
  "created_at": "2026-07-11T18:08:44.241666",
  "status": "uploaded",
  "youtube_video_id": "M_KHUirjVhQ"
}